rbpros/__init__.py
rbpros/__main__.py
rbpros/behavior.py
rbpros/device.py
rbpros/engine.py
rbpros/pin.py
rbpros/util.py
rbpros/suite/GY_271.py
rbpros/suite/HAT.py
rbpros/suite/HC_SR04.py
rbpros/suite/HP_ADDA.py
rbpros/suite/IRS_5.py
rbpros/suite/KS_RGB.py
rbpros/suite/LDR.py
rbpros/suite/MicroSwitch.py
rbpros/suite/QX_Eye.py
rbpros/suite/RBP_34.py
rbpros/suite/SG90.py
rbpros/suite/Servo2Wire.py
rbpros/suite/SingleRelay.py
rbpros/suite/__init__.py
rbpros-0.11.dist-info/DESCRIPTION.rst
rbpros-0.11.dist-info/METADATA
rbpros-0.11.dist-info/RECORD
rbpros-0.11.dist-info/WHEEL
rbpros-0.11.dist-info/entry_points.txt
rbpros-0.11.dist-info/metadata.json
rbpros-0.11.dist-info/top_level.txt
